[
  {
    "id": "t0q7a5qfi1754098872154",
    "title": "Github 自动运行任务",
    "desc": "",
    "priority": "high",
    "createdAt": 1754098872154,
    "completedAt": 1754275109148,
    "children": [],
    "level": 1
  },
  {
    "id": "t14fz2y1n1754098891952",
    "title": "日常喂养计算",
    "desc": "发小红书推广",
    "priority": "medium",
    "createdAt": 1754098891952,
    "completedAt": null,
    "children": [],
    "level": 1
  },
  {
    "id": "t2tsh2rgi1754189259454",
    "title": "个人卡片工具",
    "desc": "",
    "priority": "medium",
    "createdAt": 1754189259454,
    "completedAt": null,
    "children": [],
    "level": 1
  },
  {
    "id": "toi9mi9ji1754226254329",
    "title": "本网站添加手机端适配。",
    "desc": "",
    "priority": "medium",
    "createdAt": 1754226254329,
    "completedAt": 1754275116027,
    "children": [],
    "level": 1
  },
  {
    "id": "tblb2z9r41754301677286",
    "title": "微信群聊分析工具跑通",
    "desc": "",
    "priority": "medium",
    "createdAt": 1754301677286,
    "completedAt": null,
    "children": [],
    "level": 1
  },
  {
    "id": "tpyfbvd3h1754301727357",
    "title": "知乎帖子50W",
    "desc": "",
    "priority": "medium",
    "createdAt": 1754301727357,
    "completedAt": null,
    "children": [],
    "level": 1
  },
  {
    "id": "tnks6yqph1754307271485",
    "title": "小游戏参考网站",
    "desc": "",
    "priority": "high",
    "createdAt": 1754307271485,
    "completedAt": null,
    "children": [],
    "level": 1
  },
  {
    "id": "td7d8y3yo1754308840261",
    "title": "自动处理七麦/引力引擎数据",
    "desc": "小游戏榜单自动参考",
    "priority": "medium",
    "createdAt": 1754308840261,
    "completedAt": null,
    "children": [],
    "level": 1
  },
  {
    "id": "tplmvi9z61754382293951",
    "title": "猫咪自定义实现",
    "desc": "uchinoko-maker.jp",
    "priority": "medium",
    "createdAt": 1754382293951,
    "completedAt": null,
    "children": [],
    "level": 1
  },
  {
    "id": "tc2zplhak1754474551046",
    "title": "插件：自动获取浏览器记录",
    "desc": "生成内容",
    "priority": "medium",
    "createdAt": 1754474551046,
    "completedAt": null,
    "children": [],
    "level": 1
  },
  {
    "id": "tei6fn63n1754797097124",
    "title": "每日喂奶加设置",
    "desc": "名字、webhook、可视链接",
    "priority": "medium",
    "createdAt": 1754797097124,
    "completedAt": null,
    "children": [],
    "level": 1
  },
  {
    "id": "tniw5pyqv1754797122619",
    "title": "小游戏榜单—每小时保存",
    "desc": "",
    "priority": "low",
    "createdAt": 1754797122619,
    "completedAt": 1754995203893,
    "children": [],
    "level": 1
  },
  {
    "id": "taxl2tgfw1754801768810",
    "title": "车牌申请",
    "desc": "",
    "priority": "medium",
    "createdAt": 1754801768810,
    "completedAt": null,
    "children": [],
    "level": 1
  },
  {
    "id": "t5hg0vigq1754991490132",
    "title": "宝宝喂奶",
    "desc": "你这个记录看不到上次喂奶的时间",
    "priority": "medium",
    "createdAt": 1754991490132,
    "completedAt": 1754995202357,
    "children": [],
    "level": 1
  }
]